trendalert/__init__.py
trendalert/alert.py
trendalert-0.0.5.dist-info/LICENSE.txt
trendalert-0.0.5.dist-info/METADATA
trendalert-0.0.5.dist-info/WHEEL
trendalert-0.0.5.dist-info/top_level.txt
trendalert-0.0.5.dist-info/RECORD
