Metadata-Version: 2.1
Name: trendalert
Version: 0.0.5
Summary: Stock or Futures donchian breakout screener
Home-page: https://github.com/jonleonATX/donchian_trend_alert
Author: Jonathan Leon
Author-email: jonleonaustin@gmail.com
License: UNKNOWN
Platform: UNKNOWN
Classifier: Programming Language :: Python :: 3
Classifier: License :: OSI Approved :: MIT License
Classifier: Operating System :: OS Independent
Requires-Python: >=3.6
